{
	"today": [	
		{"name": "High Temperature", "value": "26.6", "time": "13:43", "unit": "&degC"},
		{"name": "Low Temperature", "value": "20.6", "time": "06:09", "unit": "&degC"},
		{"name": "High Wind Gust", "value": "37", "time": "12:12", "unit": " km/h"},
		{"name": "High Avg. Wind Speed", "value": "37", "time": "09:18", "unit": " km/h"},
		{"name": "Wind Run", "value": "189.1", "time": "", "unit": " km"},
		{"name": "Total Rainfall", "value": "0.0", "time": "", "unit": " mm"},
		{"name": "High Hourly Rain", "value": "0.0", "time": "00:00", "unit": " mm/hr"},
		{"name": "High Humidity", "value": "62", "time": "00:00", "unit": "%"},
		{"name": "Low Humidity", "value": "42", "time": "13:42", "unit": "%"},
		{"name": "High Dewpoint", "value": "14.0", "time": "12:01", "unit": "&degC"},
		{"name": "Low Dewpoint", "value": "12.2", "time": "08:08", "unit": "&degC"},
		{"name": "High Pressure", "value": "1014.8", "time": "11:40", "unit": " hPa"},
		{"name": "Low Pressure", "value": "1013.5", "time": "05:40", "unit": " hPa"}
		],
	"yesterday": [
		{"name": "High Temperature", "value": "27.3", "time": "15:13", "unit": "&degC"},
		{"name": "Low Temperature", "value": "14.5", "time": "00:00", "unit": "&degC"},
		{"name": "High Wind Gust", "value": "45", "time": "14:04", "unit": " km/h"},
		{"name": "High Avg. Wind Speed", "value": "42", "time": "14:03", "unit": " km/h"},
		{"name": "Wind Run", "value": "354.5", "time": "", "unit": " km"},
		{"name": "Total Rainfall", "value": "0.0", "time": "", "unit": " mm"},
		{"name": "High Hourly Rain", "value": "0.0", "time": "00:00", "unit": " mm/hr"},
		{"name": "High Humidity", "value": "90", "time": "00:00", "unit": "%"},
		{"name": "Low Humidity", "value": "42", "time": "16:18", "unit": "%"},
		{"name": "High Dewpoint", "value": "14.9", "time": "13:03", "unit": "&degC"},
		{"name": "Low Dewpoint", "value": "10.9", "time": "01:09", "unit": "&degC"},
		{"name": "High Pressure", "value": "1015.7", "time": "00:00", "unit": " hPa"},
		{"name": "Low Pressure", "value": "1012.0", "time": "15:26", "unit": " hPa"}
	]
 }  
